ledctl/__init__.py
ledctl/__main__.py
ledctl/ledctl.tar
acemagic_ledctl-0.1.1.dist-info/METADATA
acemagic_ledctl-0.1.1.dist-info/WHEEL
acemagic_ledctl-0.1.1.dist-info/entry_points.txt
acemagic_ledctl-0.1.1.dist-info/top_level.txt
acemagic_ledctl-0.1.1.dist-info/RECORD
