Metadata-Version: 2.4
Name: acemagic-ledctl
Version: 0.1.1
Summary: ACEMAGIC P9/P9 Plus (CH340) LED controller and pattern hacks
Author-email: fsncps <fsncps@eml.cc>
License-Expression: MIT
Requires-Python: >=3.8
Requires-Dist: pyserial>=3.5
